rohan_portal_gun/__init__.py
rohan_portal_gun/main.py
rohan_portal_gun-0.2.0.dist-info/METADATA
rohan_portal_gun-0.2.0.dist-info/WHEEL
rohan_portal_gun-0.2.0.dist-info/entry_points.txt
rohan_portal_gun-0.2.0.dist-info/RECORD
